abclient
